chaos_test/__init__.py
chaos_test/exceptions.py
chaos_test/hooks.py
chaos_test/parser.py
chaos_test/structure.py
tests/__init__.py
tests/conftest.py
tests/fake_app_success.py
tests/test_plugin.py
tests/test_toml_parsing.py
tests/test_yaml_parsing.py
pytest_exception_script-0.1.0.dist-info/LICENSE
pytest_exception_script-0.1.0.dist-info/METADATA
pytest_exception_script-0.1.0.dist-info/WHEEL
pytest_exception_script-0.1.0.dist-info/entry_points.txt
pytest_exception_script-0.1.0.dist-info/top_level.txt
pytest_exception_script-0.1.0.dist-info/RECORD
