Metadata-Version: 2.1
Name: pytest-exception-script
Version: 0.1.0
Summary: Walk your code through exception script to check it's resiliency to failures.
Home-page: https://github.com/qporest/pytest-exception-script
Author: qporest
Author-email: ihor.husar@gmail.com
License: UNKNOWN
Platform: UNKNOWN
Classifier: Programming Language :: Python :: 3
Classifier: Programming Language :: Python :: 2.7
Classifier: Operating System :: OS Independent
Classifier: Framework :: Pytest
Classifier: Development Status :: 3 - Alpha
Classifier: License :: OSI Approved :: GNU General Public License v3 (GPLv3)
Requires-Dist: PyYAML
Requires-Dist: toml
Requires-Dist: Werkzeug
Requires-Dist: pytest
